greatest_calculator_hits_vol_2/__init__.py
greatest_calculator_hits_vol_2/add.py
greatest_calculator_hits_vol_2/divide.py
greatest_calculator_hits_vol_2/multiply.py
greatest_calculator_hits_vol_2/subtract.py
greatest_calculator_hits_vol_2-0.1.2.dist-info/WHEEL
greatest_calculator_hits_vol_2-0.1.2.dist-info/METADATA
greatest_calculator_hits_vol_2-0.1.2.dist-info/RECORD
